docket_alarm_api_bulk_download/__init__.py
docket_alarm_api_bulk_download/__main__.py
docket_alarm_api_bulk_download/config.py
docket_alarm_api_bulk_download/fetch_updated_court_list.py
docket_alarm_api_bulk_download/file_browser.py
docket_alarm_api_bulk_download/get_json.py
docket_alarm_api_bulk_download/get_pdfs.py
docket_alarm_api_bulk_download/global_variables.py
docket_alarm_api_bulk_download/gui.py
docket_alarm_api_bulk_download/log_errors_to_table.py
docket_alarm_api_bulk_download/login.py
docket_alarm_api_bulk_download/menus.py
docket_alarm_api_bulk_download/pull_missing_docs.py
docket_alarm_api_bulk_download/__pycache__/__init__.cpython-38.pyc
docket_alarm_api_bulk_download/__pycache__/__main__.cpython-38.pyc
docket_alarm_api_bulk_download/__pycache__/config.cpython-38.pyc
docket_alarm_api_bulk_download/__pycache__/fetch_updated_court_list.cpython-38.pyc
docket_alarm_api_bulk_download/__pycache__/file_browser.cpython-38.pyc
docket_alarm_api_bulk_download/__pycache__/get_json.cpython-38.pyc
docket_alarm_api_bulk_download/__pycache__/get_pdfs.cpython-38.pyc
docket_alarm_api_bulk_download/__pycache__/global_variables.cpython-38.pyc
docket_alarm_api_bulk_download/__pycache__/gui.cpython-38.pyc
docket_alarm_api_bulk_download/__pycache__/log_errors_to_csv.cpython-38.pyc
docket_alarm_api_bulk_download/__pycache__/log_errors_to_table.cpython-38.pyc
docket_alarm_api_bulk_download/__pycache__/login.cpython-38.pyc
docket_alarm_api_bulk_download/__pycache__/main.cpython-38.pyc
docket_alarm_api_bulk_download/__pycache__/menus.cpython-38.pyc
docket_alarm_api_bulk_download/__pycache__/pull_missing_docs.cpython-38.pyc
docket_alarm_api_bulk_download/__pycache__/save_info.cpython-38.pyc
docket_alarm_api_bulk_download/csv/input.example.csv
docket_alarm_api_bulk_download/docs/courts.txt
docket_alarm_api_bulk_download/json-output/.gitkeep
docket_alarm_api_bulk_download/log/.gitkeep
docket_alarm_api_bulk_download/pdf-output/.gitkeep
docket_alarm_api_bulk_download/sav/.gitkeep
docket_alarm_api_bulk_download-0.0.1.dist-info/LICENSE
docket_alarm_api_bulk_download-0.0.1.dist-info/METADATA
docket_alarm_api_bulk_download-0.0.1.dist-info/WHEEL
docket_alarm_api_bulk_download-0.0.1.dist-info/entry_points.txt
docket_alarm_api_bulk_download-0.0.1.dist-info/top_level.txt
docket_alarm_api_bulk_download-0.0.1.dist-info/RECORD
