Metadata-Version: 2.1
Name: docket-alarm-api-bulk-download
Version: 0.0.1
Summary: Uses the Docket Alarm API to pull state court cases in bulk
Home-page: https://github.com/DocketAlarm/state-court-bulk-docket-pull
Author: Ryan Fitzpatrick
Author-email: ryanfitz514@gmail.com
License: Apache
Keywords: DOCKET,ALARM,API,BULK,DOWNLOAD,COURT,COURTS,PACER,FASTCASE
Platform: UNKNOWN
Requires-Dist: stdiomask
Requires-Dist: colorama
Requires-Dist: progress
Requires-Dist: pandas
Requires-Dist: tqdm
Requires-Dist: requests
Requires-Dist: retrying
Requires-Dist: PyPDF2
Requires-Dist: PySimpleGUI
Requires-Dist: openpyxl
